pkg/Linear_Algebra.py
pkg/__init__.py
ZhuGC_study_math-0.0.2.dist-info/LICENSE
ZhuGC_study_math-0.0.2.dist-info/METADATA
ZhuGC_study_math-0.0.2.dist-info/WHEEL
ZhuGC_study_math-0.0.2.dist-info/entry_points.txt
ZhuGC_study_math-0.0.2.dist-info/top_level.txt
ZhuGC_study_math-0.0.2.dist-info/RECORD
