Metadata-Version: 2.1
Name: ZhuGC-study-math
Version: 0.0.2
Summary: UNKNOWN
Home-page: https://github.com/gzu300
Author: zhu
Author-email: zhuguanchen@me.com
License: UNKNOWN
Platform: UNKNOWN
Classifier: Environment :: Console
Requires-Dist: numpy
